{
  "1": {
    "id": 1,
    "name": "Ира",
    "age": 22
  },
  "2": {
    "id": 2,
    "name": "Маша",
    "age": 31
  },
  "3": {
    "id": 3,
    "name": "Ира",
    "age": 21
  },
  "4": {
    "id": 4,
    "name": "Ира",
    "age": 38
  },
  "5": {
    "id": 5,
    "name": "Ира",
    "age": 44
  },
  "6": {
    "id": 6,
    "name": "Вася",
    "age": 35
  },
  "7": {
    "id": 7,
    "name": "Вася",
    "age": 32
  },
  "8": {
    "id": 8,
    "name": "Ира",
    "age": 33
  },
  "9": {
    "id": 9,
    "name": "Маша",
    "age": 22
  },
  "10": {
    "id": 10,
    "name": "Вася",
    "age": 18
  },
  "11": {
    "id": 11,
    "name": "Света",
    "age": 43
  },
  "12": {
    "id": 12,
    "name": "Света",
    "age": 37
  },
  "13": {
    "id": 13,
    "name": "Света",
    "age": 44
  },
  "14": {
    "id": 14,
    "name": "Света",
    "age": 32
  },
  "15": {
    "id": 15,
    "name": "Петя",
    "age": 44
  },
  "16": {
    "id": 16,
    "name": "Петя",
    "age": 38
  },
  "17": {
    "id": 17,
    "name": "Света",
    "age": 42
  },
  "18": {
    "id": 18,
    "name": "Ира",
    "age": 26
  },
  "19": {
    "id": 19,
    "name": "Ира",
    "age": 37
  },
  "20": {
    "id": 20,
    "name": "Света",
    "age": 24
  },
  "21": {
    "id": 21,
    "name": "Света",
    "age": 24
  },
  "22": {
    "id": 22,
    "name": "Маша",
    "age": 40
  },
  "23": {
    "id": 23,
    "name": "Петя",
    "age": 41
  },
  "24": {
    "id": 24,
    "name": "Ира",
    "age": 40
  },
  "25": {
    "id": 25,
    "name": "Петя",
    "age": 25
  },
  "26": {
    "id": 26,
    "name": "Вася",
    "age": 30
  },
  "27": {
    "id": 27,
    "name": "Света",
    "age": 25
  },
  "28": {
    "id": 28,
    "name": "Петя",
    "age": 30
  },
  "29": {
    "id": 29,
    "name": "Маша",
    "age": 45
  },
  "30": {
    "id": 30,
    "name": "Маша",
    "age": 41
  },
  "31": {
    "id": 31,
    "name": "Маша",
    "age": 39
  },
  "32": {
    "id": 32,
    "name": "Вася",
    "age": 44
  },
  "33": {
    "id": 33,
    "name": "Маша",
    "age": 35
  },
  "34": {
    "id": 34,
    "name": "Света",
    "age": 37
  },
  "35": {
    "id": 35,
    "name": "Вася",
    "age": 21
  },
  "36": {
    "id": 36,
    "name": "Ира",
    "age": 40
  },
  "37": {
    "id": 37,
    "name": "Ира",
    "age": 38
  },
  "38": {
    "id": 38,
    "name": "Петя",
    "age": 31
  },
  "39": {
    "id": 39,
    "name": "Маша",
    "age": 44
  },
  "40": {
    "id": 40,
    "name": "Вася",
    "age": 19
  },
  "41": {
    "id": 41,
    "name": "Петя",
    "age": 40
  },
  "42": {
    "id": 42,
    "name": "Ира",
    "age": 43
  },
  "43": {
    "id": 43,
    "name": "Маша",
    "age": 38
  },
  "44": {
    "id": 44,
    "name": "Петя",
    "age": 21
  },
  "45": {
    "id": 45,
    "name": "Вася",
    "age": 30
  },
  "46": {
    "id": 46,
    "name": "Вася",
    "age": 28
  },
  "47": {
    "id": 47,
    "name": "Ира",
    "age": 40
  },
  "48": {
    "id": 48,
    "name": "Маша",
    "age": 45
  },
  "49": {
    "id": 49,
    "name": "Света",
    "age": 19
  },
  "50": {
    "id": 50,
    "name": "Ира",
    "age": 40
  }
}